cn4_instrument_common/__init__.py
cn4_instrument_common/common.py
cn4_instrument_common/decorator.py
cn4_instrument_common/error.py
cn4_instrument_common/event.py
cn4_instrument_common/timer.py
cn4_instrument_common-0.0.3.dist-info/DESCRIPTION.rst
cn4_instrument_common-0.0.3.dist-info/METADATA
cn4_instrument_common-0.0.3.dist-info/RECORD
cn4_instrument_common-0.0.3.dist-info/WHEEL
cn4_instrument_common-0.0.3.dist-info/metadata.json
cn4_instrument_common-0.0.3.dist-info/top_level.txt
tests/__init__.py
tests/test_decorator.py
tests/test_entity.py
tests/test_entitydescription.py
tests/test_entitydictionary.py
tests/test_timer.py
