Metadata-Version: 2.0
Name: cn4-instrument-common
Version: 0.0.3
Summary: Package with support functions and artifacts for measuring instrument     development
Home-page: UNKNOWN
Author: cinderella
License: UNKNOWN
Platform: UNKNOWN
Classifier: Programming Language :: Python :: 3
Classifier: License :: OSI Approved :: MIT License
Classifier: Operating System :: OS Independent
